{
  "project_info": {
    "project_number": "473300758797",
    "project_id": "hotel-7e2d2",
    "storage_bucket": "hotel-7e2d2.appspot.com"
  },
  "client": [
    {
      "client_info": {
        "mobilesdk_app_id": "1:473300758797:android:13d5bff94d27c0357ec044",
        "android_client_info": {
          "package_name": "com.example.hotel_management"
        }
      },
      "oauth_client": [],
      "api_key": [
        {
          "current_key": "AIzaSyBRtX6EFdNx0teS7lHHaG8I6w0IQbVHnMA"
        }
      ],
      "services": {
        "appinvite_service": {
          "other_platform_oauth_client": []
        }
      }
    }
  ],
  "configuration_version": "1"
}